includesource/IncludeSource.py
includesource/__init__.py
trac_IncludeSource-0.5.1.dist-info/LICENSE
trac_IncludeSource-0.5.1.dist-info/METADATA
trac_IncludeSource-0.5.1.dist-info/WHEEL
trac_IncludeSource-0.5.1.dist-info/entry_points.txt
trac_IncludeSource-0.5.1.dist-info/top_level.txt
trac_IncludeSource-0.5.1.dist-info/RECORD
