Metadata-Version: 2.1
Name: trac-IncludeSource
Version: 0.5.1
Summary: Include (parts of) a source file into the current wiki page
Home-page: http://trac-hacks.org/wiki/IncludeSourcePartialPlugin
Author: Chris Heller
Maintainer: Thomas Tressieres
Maintainer-email: ttressieres@gmail.com
License: BSD
Platform: UNKNOWN
Classifier: Programming Language :: Python :: 2
Classifier: Operating System :: OS Independent
Classifier: Framework :: Trac
Requires-Dist: Trac
